MANIFEST.in
README.rst
setup.py
smokematic/__init__.py
smokematic/baster.py
smokematic/blower.py
smokematic/controller.py
smokematic/probe.py
smokematic/web.py
smokematic.egg-info/PKG-INFO
smokematic.egg-info/SOURCES.txt
smokematic.egg-info/dependency_links.txt
smokematic.egg-info/entry_points.txt
smokematic.egg-info/not-zip-safe
smokematic.egg-info/requires.txt
smokematic.egg-info/top_level.txt
smokematic/skel/config.json
smokematic/webgui/index.html
smokematic/webgui/css/bootstrap-theme.min.css
smokematic/webgui/css/bootstrap.min.css
smokematic/webgui/css/main.css
smokematic/webgui/fonts/glyphicons-halflings-regular.eot
smokematic/webgui/fonts/glyphicons-halflings-regular.svg
smokematic/webgui/fonts/glyphicons-halflings-regular.ttf
smokematic/webgui/fonts/glyphicons-halflings-regular.woff
smokematic/webgui/js/additional-methods.min.js
smokematic/webgui/js/bootstrap.min.js
smokematic/webgui/js/excanvas.min.js
smokematic/webgui/js/jquery.flot.axislabels.js
smokematic/webgui/js/jquery.flot.min.js
smokematic/webgui/js/jquery.flot.resize.min.js
smokematic/webgui/js/jquery.min.js
smokematic/webgui/js/jquery.validate.min.js
smokematic/webgui/js/smokematic.js