Metadata-Version: 1.1
Name: smokematic
Version: 0.1.0
Summary: A smoking (cooking) automation system built on the Beaglebone Black
Home-page: https://github.com/Caligatio/smokematic
Author: Brian Turek
Author-email: brian.turek@gmail.com
License: BSD
Platform: UNKNOWN
Classifier: License :: OSI Approved :: BSD License
Classifier: Development Status :: 4 - Beta
Classifier: Operating System :: POSIX :: Linux
Classifier: Programming Language :: Python :: 2
Classifier: Programming Language :: JavaScript
Classifier: Topic :: Home Automation
Classifier: Topic :: Software Development :: Embedded Systems
